WhatAnime/__init__.py
WhatAnime/exception.py
WhatAnime/types.py
WhatAnime/whatanime.py
python_whatanime-0.1.2.dist-info/LICENSE
python_whatanime-0.1.2.dist-info/METADATA
python_whatanime-0.1.2.dist-info/WHEEL
python_whatanime-0.1.2.dist-info/top_level.txt
python_whatanime-0.1.2.dist-info/RECORD
