Metadata-Version: 2.1
Name: python-whatanime
Version: 0.1.2
Summary: An Unofficial python wrapper for trace.moe
Home-page: https://github.com/Black-Bulls-Bots/WhatAnime
Author: Joker Hacker
Author-email: jokerhacker.6521@protonmail.com
License: License :: OSI Approved :: GNU Lesser General Public License v3 (LGPLv3)
Project-URL: Discussion, https://t.me/blackbulls_support
Platform: UNKNOWN
Requires-Python: >=3.8
License-File: LICENSE
Requires-Dist: requests
